staticat/__init__.py
staticat/__main__.py
staticat/lib.py
staticat/templates/catalog.html
staticat/templates/catalog.rdf
staticat/templates/dataset.html
staticat/templates/default.css
staticat/vocab/__init__.py
staticat/vocab/availability.rdf
staticat/vocab/data-theme.rdf
staticat/vocab/file-type.xml
staticat/vocab/license.rdf
staticat-0.0.9.dist-info/licenses/LICENSE
staticat-0.0.9.dist-info/METADATA
staticat-0.0.9.dist-info/WHEEL
staticat-0.0.9.dist-info/entry_points.txt
staticat-0.0.9.dist-info/top_level.txt
staticat-0.0.9.dist-info/RECORD
