Metadata-Version: 2.4
Name: staticat
Version: 0.0.9
Summary: Generate static open data catalogs according to the DCAT-AP.de standard
Author-email: Hannes Riebl <hriebl@posteo.de>
Project-URL: Homepage, https://github.com/hriebl/staticat
Project-URL: Issues, https://github.com/hriebl/staticat/issues
Classifier: Programming Language :: Python :: 3
Classifier: License :: OSI Approved :: MIT License
Classifier: Operating System :: OS Independent
Requires-Python: >=3.9
License-File: LICENSE
Requires-Dist: Jinja2>=3.1
Requires-Dist: markdown-it-py>=3.0
Requires-Dist: openpyxl>=3.1
Requires-Dist: pandas>=2.2
Requires-Dist: pydantic>=2.8
Requires-Dist: rdflib>=7.0
Requires-Dist: tomli>=2.2; python_version < "3.11"
Provides-Extra: dev
Requires-Dist: pre-commit>=3.7; extra == "dev"
Requires-Dist: pyinstaller>=6.9; extra == "dev"
Dynamic: license-file
